osiris/__init__.py
osiris/adapters/__init__.py
osiris/adapters/ingress_adapter.py
osiris/adapters/sap_service.py
osiris/apis/__init__.py
osiris/apis/dependencies.py
osiris/apis/egress.py
osiris/apis/ingress.py
osiris/core/__init__.py
osiris/core/azure_client_authorization.py
osiris/core/configuration.py
osiris/core/enums.py
osiris/core/instrumentation.py
osiris/core/io.py
osiris/pipelines/__init__.py
osiris/pipelines/azure_data_storage.py
osiris/pipelines/file_io_connector.py
osiris/pipelines/transformations.py
osiris/validation/__init__.py
osiris/validation/data_validation.py
osiris_sdk-1.0.13.dist-info/LICENSE
osiris_sdk-1.0.13.dist-info/METADATA
osiris_sdk-1.0.13.dist-info/WHEEL
osiris_sdk-1.0.13.dist-info/top_level.txt
osiris_sdk-1.0.13.dist-info/RECORD
