Metadata-Version: 2.1
Name: osiris-sdk
Version: 1.0.13
Summary: Python SDK for Osiris (Energinet DataPlatform).
Home-page: https://github.com/Open-Dataplatform/osiris-sdk.git
Author: Energinet DataPlatform
Author-email: dataplatform@energinet.dk
License: UNKNOWN
Project-URL: Bug Tracker, https://github.com/Open-Dataplatform/osiris-sdk.git/issues
Platform: UNKNOWN
Classifier: Programming Language :: Python :: 3
Classifier: License :: OSI Approved :: MIT License
Classifier: Operating System :: OS Independent
Requires-Python: <3.9,>=3.6
License-File: LICENSE
Requires-Dist: msal
Requires-Dist: requests
Requires-Dist: azure-identity
Requires-Dist: apache-beam
Requires-Dist: azure-storage-file-datalake
Requires-Dist: pandas
Requires-Dist: prometheus-client
Requires-Dist: aiohttp
Requires-Dist: pyarrow
Requires-Dist: jaeger-client
Requires-Dist: opentracing
